{"id": "7650121317510341354", "title": "感觉这地方有魔力就算不化妆也拍的很好看 #apink #nonono #dance #抖音潮流舞蹈大赛 #Rightcell牛仔裤", "description": "感觉这地方有魔力就算不化妆也拍的很好看 #apink #nonono #dance #抖音潮流舞蹈大赛 #Rightcell牛仔裤", "timestamp": 1781182671, "view_count": 0, "like_count": 5931, "repost_count": 273, "comment_count": 122, "save_count": 647, "uploader": "yli_328", "uploader_id": "4389696557548080", "channel": "引力", "channel_id": "MS4wLjABAAAA3UVVHcSnCPhVaCG3Oo5oFMo2QNLocidtJckP8_tTpPGpC9K9MKAsbpl2Ugdv1Vie", "channel_url": "https://www.douyin.com/user/MS4wLjABAAAA3UVVHcSnCPhVaCG3Oo5oFMo2QNLocidtJckP8_tTpPGpC9K9MKAsbpl2Ugdv1Vie", "uploader_url": "https://www.douyin.com/user/yli_328", "track": "NoNoNo", "album": "Secret Garden", "artists": ["Apink"], "formats": [{"url": "https://api-play.amemv.com/aweme/v1/play/?video_id=v0d00fg10000d8lb1h7og65k81lq6c00&line=0&ratio=540p&watermark=1&media_type=4&vr_type=0&improve_bitrate=0&biz_sign=NRPI1lC4AlkgB1YZ_o3JkfAfESRKvePEcuabqtxlfCqwTcZpAsEAnNtB8eSE9VaaOzLa7CA0Ou-V1V2BgVcWetIR5E7HDGbNHaUZIZuaRMUGyO7s5wbVW7et0I2xs1hA&logo_name=aweme_search_suffix&source=PackSourceEnum_AWEME_DETAIL", "filesize": 4058479, "ext": "mp4", "acodec": "aac", "source_preference": -2, "format_id": "download_addr-0", "format_note": "Download video, watermarked (API)", "vcodec": "h264", "width": 720, "height": 1280, "preference": -1, "protocol": "https", "video_ext": "mp4", "audio_ext": "none", "resolution": "720x1280", "dynamic_range": "SDR", "aspect_ratio": 0.56, "cookies": "sid_tt=15444ec40fa77551c3ec42e9c3a92c10; Domain=api-play.amemv.com; Path=/", "http_headers": {"User-Agent": "Mozilla/5.0 (Macintosh; Intel Mac OS X 10_15_7) AppleWebKit/537.36 (KHTML, like Gecko) Chrome/147.0.0.0 Safari/537.36 Edg/147.0.0.0", "Accept": "text/html,application/xhtml+xml,application/xml;q=0.9,*/*;q=0.8", "Accept-Language": "en-us,en;q=0.5", "Sec-Fetch-Mode": "navigate", "Referer": "https://www.douyin.com/"}, "format": "download_addr-0 - 720x1280 (Download video, watermarked (API))"}, {"url": "https://api.amemv.com/aweme/v1/play/?video_id=v0d00fg10000d8lb1h7og65k81lq6c00&line=1&ratio=540p&watermark=1&media_type=4&vr_type=0&improve_bitrate=0&biz_sign=NRPI1lC4AlkgB1YZ_o3JkfAfESRKvePEcuabqtxlfCqwTcZpAsEAnNtB8eSE9VaaOzLa7CA0Ou-V1V2BgVcWetIR5E7HDGbNHaUZIZuaRMUGyO7s5wbVW7et0I2xs1hA&logo_name=aweme_search_suffix&source=PackSourceEnum_AWEME_DETAIL", "filesize": 4058479, "ext": "mp4", "acodec": "aac", "source_preference": -2, "format_id": "download_addr-1", "format_note": "Download video, watermarked (API)", "vcodec": "h264", "width": 720, "height": 1280, "preference": -1, "protocol": "https", "video_ext": "mp4", "audio_ext": "none", "resolution": "720x1280", "dynamic_range": "SDR", "aspect_ratio": 0.56, "cookies": "sid_tt=15444ec40fa77551c3ec42e9c3a92c10; Domain=api.amemv.com; Path=/", "http_headers": {"User-Agent": "Mozilla/5.0 (Macintosh; Intel Mac OS X 10_15_7) AppleWebKit/537.36 (KHTML, like Gecko) Chrome/147.0.0.0 Safari/537.36 Edg/147.0.0.0", "Accept": "text/html,application/xhtml+xml,application/xml;q=0.9,*/*;q=0.8", "Accept-Language": "en-us,en;q=0.5", "Sec-Fetch-Mode": "navigate", "Referer": "https://www.douyin.com/"}, "format": "download_addr-1 - 720x1280 (Download video, watermarked (API))"}, {"url": "https://v11-default.365yg.com/6e87a9b178188fb60437bffb0b0c9945/6a61122c/video/tos/cn/tos-cn-ve-15/oEsoEqfegTftzywAlA2BqCBe2MroYCAED4LEA0/?a=0&ch=26&cr=3&dr=0&lr=all&cd=0%7C0%7C0%7C3&cv=1&br=998&bt=998&cs=0&ds=3&ft=_7BMvR89AARXP2b6.uCd.FGcvk3.-I6Ee6AlH63TMoxJutAWPPqXteWiRtyaRfqs&mime_type=video_mp4&qs=0&rc=NTRmOjM8ODszNWg3ZjhkaUBpM2Z0NG45cmtlOzMzNGkzM0BhYjYwXjAzX2IxNl4vMDVgYSMtM2k1MmQ0LmlhLS1kLWFzcw%3D%3D&btag=80000e00010000&cquery=100H_100F_100E_103t_100I&dy_q=1784742912&feature_id=93c5283e1794c821af5e0ee1411bec9d&l=20260723015512FEC51E91C1EF8FE58A41", "filesize": 4058479, "ext": "mp4", "acodec": "aac", "source_preference": -1, "format_id": "download_addr-2", "format_note": "Download video, watermarked", "vcodec": "h264", "width": 720, "height": 1280, "preference": -1, "protocol": "https", "video_ext": "mp4", "audio_ext": "none", "resolution": "720x1280", "dynamic_range": "SDR", "aspect_ratio": 0.56, "cookies": "sid_tt=15444ec40fa77551c3ec42e9c3a92c10; Domain=v11-default.365yg.com; Path=/", "http_headers": {"User-Agent": "Mozilla/5.0 (Macintosh; Intel Mac OS X 10_15_7) AppleWebKit/537.36 (KHTML, like Gecko) Chrome/147.0.0.0 Safari/537.36 Edg/147.0.0.0", "Accept": "text/html,application/xhtml+xml,application/xml;q=0.9,*/*;q=0.8", "Accept-Language": "en-us,en;q=0.5", "Sec-Fetch-Mode": "navigate", "Referer": "https://www.douyin.com/"}, "format": "download_addr-2 - 720x1280 (Download video, watermarked)"}, {"url": "https://v95-ynkmtc-default.365yg.com/50d4a8116b79e543fa0410dcd04403d4/6a61122c/video/tos/cn/tos-cn-ve-15/oEsoEqfegTftzywAlA2BqCBe2MroYCAED4LEA0/?a=0&ch=26&cr=3&dr=0&lr=all&cd=0%7C0%7C0%7C3&cv=1&br=998&bt=998&cs=0&ds=3&ft=_7BMvR89AARXP2b6.uCd.FGcvk3.-I6Ee6AlH63TMoxJutAWPPqXteWiRtyaRfqs&mime_type=video_mp4&qs=0&rc=NTRmOjM8ODszNWg3ZjhkaUBpM2Z0NG45cmtlOzMzNGkzM0BhYjYwXjAzX2IxNl4vMDVgYSMtM2k1MmQ0LmlhLS1kLWFzcw%3D%3D&btag=80000e00010000&cquery=103t_100I_100H_100F_100E&dy_q=1784742912&feature_id=93c5283e1794c821af5e0ee1411bec9d&l=20260723015512FEC51E91C1EF8FE58A41", "filesize": 4058479, "ext": "mp4", "acodec": "aac", "source_preference": -1, "format_id": "download_addr-3", "format_note": "Download video, watermarked", "vcodec": "h264", "width": 720, "height": 1280, "preference": -1, "protocol": "https", "video_ext": "mp4", "audio_ext": "none", "resolution": "720x1280", "dynamic_range": "SDR", "aspect_ratio": 0.56, "cookies": "sid_tt=15444ec40fa77551c3ec42e9c3a92c10; Domain=v95-ynkmtc-default.365yg.com; Path=/", "http_headers": {"User-Agent": "Mozilla/5.0 (Macintosh; Intel Mac OS X 10_15_7) AppleWebKit/537.36 (KHTML, like Gecko) Chrome/147.0.0.0 Safari/537.36 Edg/147.0.0.0", "Accept": "text/html,application/xhtml+xml,application/xml;q=0.9,*/*;q=0.8", "Accept-Language": "en-us,en;q=0.5", "Sec-Fetch-Mode": "navigate", "Referer": "https://www.douyin.com/"}, "format": "download_addr-3 - 720x1280 (Download video, watermarked)"}, {"url": "https://api-play.amemv.com/aweme/v1/play/?video_id=v0d00fg10000d8lb1h7og65k81lq6c00&line=0&file_id=ee0910331d48494bb55243e1922f7117&sign=7b6709c6dd8d04e5691b450ce841778a&is_play_url=1&source=PackSourceEnum_AWEME_DETAIL", "filesize": 2507990, "ext": "mp4", "acodec": "aac", "source_preference": -2, "format_id": "h264_540p_697996-0", "format_note": "Direct video (API)", "vcodec": "h264", "width": 576, "height": 1024, "tbr": 697, "quality": 1, "preference": -1, "protocol": "https", "video_ext": "mp4", "audio_ext": "none", "resolution": "576x1024", "dynamic_range": "SDR", "aspect_ratio": 0.56, "cookies": "sid_tt=15444ec40fa77551c3ec42e9c3a92c10; Domain=api-play.amemv.com; Path=/", "http_headers": {"User-Agent": "Mozilla/5.0 (Macintosh; Intel Mac OS X 10_15_7) AppleWebKit/537.36 (KHTML, like Gecko) Chrome/147.0.0.0 Safari/537.36 Edg/147.0.0.0", "Accept": "text/html,application/xhtml+xml,application/xml;q=0.9,*/*;q=0.8", "Accept-Language": "en-us,en;q=0.5", "Sec-Fetch-Mode": "navigate", "Referer": "https://www.douyin.com/"}, "format": "h264_540p_697996-0 - 576x1024 (Direct video (API))"}, {"url": "https://api.amemv.com/aweme/v1/play/?video_id=v0d00fg10000d8lb1h7og65k81lq6c00&line=1&file_id=ee0910331d48494bb55243e1922f7117&sign=7b6709c6dd8d04e5691b450ce841778a&is_play_url=1&source=PackSourceEnum_AWEME_DETAIL", "filesize": 2507990, "ext": "mp4", "acodec": "aac", "source_preference": -2, "format_id": "h264_540p_697996-1", "format_note": "Direct video (API)", "vcodec": "h264", "width": 576, "height": 1024, "tbr": 697, "quality": 1, "preference": -1, "protocol": "https", "video_ext": "mp4", "audio_ext": "none", "resolution": "576x1024", "dynamic_range": "SDR", "aspect_ratio": 0.56, "cookies": "sid_tt=15444ec40fa77551c3ec42e9c3a92c10; Domain=api.amemv.com; Path=/", "http_headers": {"User-Agent": "Mozilla/5.0 (Macintosh; Intel Mac OS X 10_15_7) AppleWebKit/537.36 (KHTML, like Gecko) Chrome/147.0.0.0 Safari/537.36 Edg/147.0.0.0", "Accept": "text/html,application/xhtml+xml,application/xml;q=0.9,*/*;q=0.8", "Accept-Language": "en-us,en;q=0.5", "Sec-Fetch-Mode": "navigate", "Referer": "https://www.douyin.com/"}, "format": "h264_540p_697996-1 - 576x1024 (Direct video (API))"}, {"url": "https://v11-default.365yg.com/24ec42fb9f48480d4970a8041b3adbae/6a61122c/video/tos/cn/tos-cn-ve-15/ogLCMPii2wBxIG0EQaQZQFjuxmAqiETqZAIPA/?a=0&ch=26&cr=3&dr=0&lr=all&cd=0%7C0%7C0%7C3&cv=1&br=681&bt=681&cs=0&ds=6&ft=_7BMvR89AARXP2b6.uCd.FGcvk3.-I6Ee6AlH63TMoxJutAWPPqXteWiRtyaRfqs&mime_type=video_mp4&qs=0&rc=OjRpNTQ2NThlPDtnNjM8aEBpM2Z0NG45cmtlOzMzNGkzM0AuNC82YjEyXzExMS4wLi1iYSMtM2k1MmQ0LmlhLS1kLWFzcw%3D%3D&btag=80000e00010000&cquery=100I_100H_100F_100E_103t&dy_q=1784742912&feature_id=f0150a16a324336cda5d6dd0b69ed299&l=20260723015512FEC51E91C1EF8FE58A41", "filesize": 2507990, "ext": "mp4", "acodec": "aac", "source_preference": -1, "format_id": "h264_540p_697996-2", "format_note": "Direct video", "vcodec": "h264", "width": 576, "height": 1024, "tbr": 697, "quality": 1, "preference": -1, "protocol": "https", "video_ext": "mp4", "audio_ext": "none", "resolution": "576x1024", "dynamic_range": "SDR", "aspect_ratio": 0.56, "cookies": "sid_tt=15444ec40fa77551c3ec42e9c3a92c10; Domain=v11-default.365yg.com; Path=/", "http_headers": {"User-Agent": "Mozilla/5.0 (Macintosh; Intel Mac OS X 10_15_7) AppleWebKit/537.36 (KHTML, like Gecko) Chrome/147.0.0.0 Safari/537.36 Edg/147.0.0.0", "Accept": "text/html,application/xhtml+xml,application/xml;q=0.9,*/*;q=0.8", "Accept-Language": "en-us,en;q=0.5", "Sec-Fetch-Mode": "navigate", "Referer": "https://www.douyin.com/"}, "format": "h264_540p_697996-2 - 576x1024 (Direct video)"}, {"url": "https://v95-ynkmtc-default.365yg.com/2109e91d493372b6500171ccd6b1b1da/6a61122c/video/tos/cn/tos-cn-ve-15/ogLCMPii2wBxIG0EQaQZQFjuxmAqiETqZAIPA/?a=0&ch=26&cr=3&dr=0&lr=all&cd=0%7C0%7C0%7C3&cv=1&br=681&bt=681&cs=0&ds=6&ft=_7BMvR89AARXP2b6.uCd.FGcvk3.-I6Ee6AlH63TMoxJutAWPPqXteWiRtyaRfqs&mime_type=video_mp4&qs=0&rc=OjRpNTQ2NThlPDtnNjM8aEBpM2Z0NG45cmtlOzMzNGkzM0AuNC82YjEyXzExMS4wLi1iYSMtM2k1MmQ0LmlhLS1kLWFzcw%3D%3D&btag=80000e00010000&cquery=100I_100H_100F_100E_103t&dy_q=1784742912&feature_id=f0150a16a324336cda5d6dd0b69ed299&l=20260723015512FEC51E91C1EF8FE58A41", "filesize": 2507990, "ext": "mp4", "acodec": "aac", "source_preference": -1, "format_id": "h264_540p_697996-3", "format_note": "Direct video", "vcodec": "h264", "width": 576, "height": 1024, "tbr": 697, "quality": 1, "preference": -1, "protocol": "https", "video_ext": "mp4", "audio_ext": "none", "resolution": "576x1024", "dynamic_range": "SDR", "aspect_ratio": 0.56, "cookies": "sid_tt=15444ec40fa77551c3ec42e9c3a92c10; Domain=v95-ynkmtc-default.365yg.com; Path=/", "http_headers": {"User-Agent": "Mozilla/5.0 (Macintosh; Intel Mac OS X 10_15_7) AppleWebKit/537.36 (KHTML, like Gecko) Chrome/147.0.0.0 Safari/537.36 Edg/147.0.0.0", "Accept": "text/html,application/xhtml+xml,application/xml;q=0.9,*/*;q=0.8", "Accept-Language": "en-us,en;q=0.5", "Sec-Fetch-Mode": "navigate", "Referer": "https://www.douyin.com/"}, "format": "h264_540p_697996-3 - 576x1024 (Direct video)"}, {"url": "https://api-play.amemv.com/aweme/v1/play/?video_id=v0d00fg10000d8lb1h7og65k81lq6c00&line=0&file_id=ee8c44ca46e24b55b6800f7de9617385&sign=c9444189b71f39ed9d9e25c55565b1d2&is_play_url=1&source=PackSourceEnum_AWEME_DETAIL", "filesize": 530528, "ext": "mp4", "acodec": "aac", "source_preference": -2, "format_id": "bytevc1_540p_147640-0", "format_note": "Playback video (API)", "tbr": 147, "vcodec": "h265", "fps": 30, "height": 1024, "quality": 1, "width": 576, "preference": -1, "protocol": "https", "video_ext": "mp4", "audio_ext": "none", "resolution": "576x1024", "dynamic_range": "SDR", "aspect_ratio": 0.56, "cookies": "sid_tt=15444ec40fa77551c3ec42e9c3a92c10; Domain=api-play.amemv.com; Path=/", "http_headers": {"User-Agent": "Mozilla/5.0 (Macintosh; Intel Mac OS X 10_15_7) AppleWebKit/537.36 (KHTML, like Gecko) Chrome/147.0.0.0 Safari/537.36 Edg/147.0.0.0", "Accept": "text/html,application/xhtml+xml,application/xml;q=0.9,*/*;q=0.8", "Accept-Language": "en-us,en;q=0.5", "Sec-Fetch-Mode": "navigate", "Referer": "https://www.douyin.com/"}, "format": "bytevc1_540p_147640-0 - 576x1024 (Playback video (API))"}, {"url": "https://api.amemv.com/aweme/v1/play/?video_id=v0d00fg10000d8lb1h7og65k81lq6c00&line=1&file_id=ee8c44ca46e24b55b6800f7de9617385&sign=c9444189b71f39ed9d9e25c55565b1d2&is_play_url=1&source=PackSourceEnum_AWEME_DETAIL", "filesize": 530528, "ext": "mp4", "acodec": "aac", "source_preference": -2, "format_id": "bytevc1_540p_147640-1", "format_note": "Playback video (API)", "tbr": 147, "vcodec": "h265", "fps": 30, "height": 1024, "quality": 1, "width": 576, "preference": -1, "protocol": "https", "video_ext": "mp4", "audio_ext": "none", "resolution": "576x1024", "dynamic_range": "SDR", "aspect_ratio": 0.56, "cookies": "sid_tt=15444ec40fa77551c3ec42e9c3a92c10; Domain=api.amemv.com; Path=/", "http_headers": {"User-Agent": "Mozilla/5.0 (Macintosh; Intel Mac OS X 10_15_7) AppleWebKit/537.36 (KHTML, like Gecko) Chrome/147.0.0.0 Safari/537.36 Edg/147.0.0.0", "Accept": "text/html,application/xhtml+xml,application/xml;q=0.9,*/*;q=0.8", "Accept-Language": "en-us,en;q=0.5", "Sec-Fetch-Mode": "navigate", "Referer": "https://www.douyin.com/"}, "format": "bytevc1_540p_147640-1 - 576x1024 (Playback video (API))"}, {"url": "https://v11-default.365yg.com/7afff43f05defcc18ec3e55e0cc4e30c/6a61122c/video/tos/cn/tos-cn-ve-15/ogAqGqMiGBETjIaIAGXQuEAwP8iAP0ExQjipI/?a=0&ch=26&cr=3&dr=0&lr=all&cd=0%7C0%7C0%7C3&cv=1&br=144&bt=144&cs=2&ds=6&ft=_7BMvR89AARXP2b6.uCd.FGcvk3.-I6Ee6AlH63TMoxJutAWPPqXteWiRtyaRfqs&mime_type=video_mp4&qs=0&rc=ODY0PGdpMzk4ZTU5ZDdmaEBpM2Z0NG45cmtlOzMzNGkzM0A1NDNiNC01XzIxYjFgMTViYSMtM2k1MmQ0LmlhLS1kLWFzcw%3D%3D&btag=80000e00010000&cquery=100F_100E_103t_100I_100H&dy_q=1784742912&feature_id=a2a5bfc4019936dfb9929db9339ed4a8&l=20260723015512FEC51E91C1EF8FE58A41", "filesize": 530528, "ext": "mp4", "acodec": "aac", "source_preference": -1, "format_id": "bytevc1_540p_147640-2", "format_note": "Playback video", "tbr": 147, "vcodec": "h265", "fps": 30, "height": 1024, "quality": 1, "width": 576, "preference": -1, "protocol": "https", "video_ext": "mp4", "audio_ext": "none", "resolution": "576x1024", "dynamic_range": "SDR", "aspect_ratio": 0.56, "cookies": "sid_tt=15444ec40fa77551c3ec42e9c3a92c10; Domain=v11-default.365yg.com; Path=/", "http_headers": {"User-Agent": "Mozilla/5.0 (Macintosh; Intel Mac OS X 10_15_7) AppleWebKit/537.36 (KHTML, like Gecko) Chrome/147.0.0.0 Safari/537.36 Edg/147.0.0.0", "Accept": "text/html,application/xhtml+xml,application/xml;q=0.9,*/*;q=0.8", "Accept-Language": "en-us,en;q=0.5", "Sec-Fetch-Mode": "navigate", "Referer": "https://www.douyin.com/"}, "format": "bytevc1_540p_147640-2 - 576x1024 (Playback video)"}, {"url": "https://v95-ynkmtc-default.365yg.com/9678ad8b31ecc008fc2e247dbff3f19b/6a61122c/video/tos/cn/tos-cn-ve-15/ogAqGqMiGBETjIaIAGXQuEAwP8iAP0ExQjipI/?a=0&ch=26&cr=3&dr=0&lr=all&cd=0%7C0%7C0%7C3&cv=1&br=144&bt=144&cs=2&ds=6&ft=_7BMvR89AARXP2b6.uCd.FGcvk3.-I6Ee6AlH63TMoxJutAWPPqXteWiRtyaRfqs&mime_type=video_mp4&qs=0&rc=ODY0PGdpMzk4ZTU5ZDdmaEBpM2Z0NG45cmtlOzMzNGkzM0A1NDNiNC01XzIxYjFgMTViYSMtM2k1MmQ0LmlhLS1kLWFzcw%3D%3D&btag=80000e00010000&cquery=100F_100E_103t_100I_100H&dy_q=1784742912&feature_id=a2a5bfc4019936dfb9929db9339ed4a8&l=20260723015512FEC51E91C1EF8FE58A41", "filesize": 530528, "ext": "mp4", "acodec": "aac", "source_preference": -1, "format_id": "bytevc1_540p_147640-3", "format_note": "Playback video", "tbr": 147, "vcodec": "h265", "fps": 30, "height": 1024, "quality": 1, "width": 576, "preference": -1, "protocol": "https", "video_ext": "mp4", "audio_ext": "none", "resolution": "576x1024", "dynamic_range": "SDR", "aspect_ratio": 0.56, "cookies": "sid_tt=15444ec40fa77551c3ec42e9c3a92c10; Domain=v95-ynkmtc-default.365yg.com; Path=/", "http_headers": {"User-Agent": "Mozilla/5.0 (Macintosh; Intel Mac OS X 10_15_7) AppleWebKit/537.36 (KHTML, like Gecko) Chrome/147.0.0.0 Safari/537.36 Edg/147.0.0.0", "Accept": "text/html,application/xhtml+xml,application/xml;q=0.9,*/*;q=0.8", "Accept-Language": "en-us,en;q=0.5", "Sec-Fetch-Mode": "navigate", "Referer": "https://www.douyin.com/"}, "format": "bytevc1_540p_147640-3 - 576x1024 (Playback video)"}, {"url": "https://api-play.amemv.com/aweme/v1/play/?video_id=v0d00fg10000d8lb1h7og65k81lq6c00&line=0&file_id=e866c08937ce4ba6b9671e439cdff4d7&sign=d8fae088321e57fcc22aff08674efa89&is_play_url=1&source=PackSourceEnum_AWEME_DETAIL", "filesize": 1138827, "ext": "mp4", "acodec": "aac", "source_preference": -2, "format_id": "bytevc1_540p_316924-0", "format_note": "Playback video (API)", "tbr": 316, "vcodec": "h265", "fps": 30, "height": 1024, "quality": 1, "width": 576, "preference": -1, "protocol": "https", "video_ext": "mp4", "audio_ext": "none", "resolution": "576x1024", "dynamic_range": "SDR", "aspect_ratio": 0.56, "cookies": "sid_tt=15444ec40fa77551c3ec42e9c3a92c10; Domain=api-play.amemv.com; Path=/", "http_headers": {"User-Agent": "Mozilla/5.0 (Macintosh; Intel Mac OS X 10_15_7) AppleWebKit/537.36 (KHTML, like Gecko) Chrome/147.0.0.0 Safari/537.36 Edg/147.0.0.0", "Accept": "text/html,application/xhtml+xml,application/xml;q=0.9,*/*;q=0.8", "Accept-Language": "en-us,en;q=0.5", "Sec-Fetch-Mode": "navigate", "Referer": "https://www.douyin.com/"}, "format": "bytevc1_540p_316924-0 - 576x1024 (Playback video (API))"}, {"url": "https://api.amemv.com/aweme/v1/play/?video_id=v0d00fg10000d8lb1h7og65k81lq6c00&line=1&file_id=e866c08937ce4ba6b9671e439cdff4d7&sign=d8fae088321e57fcc22aff08674efa89&is_play_url=1&source=PackSourceEnum_AWEME_DETAIL", "filesize": 1138827, "ext": "mp4", "acodec": "aac", "source_preference": -2, "format_id": "bytevc1_540p_316924-1", "format_note": "Playback video (API)", "tbr": 316, "vcodec": "h265", "fps": 30, "height": 1024, "quality": 1, "width": 576, "preference": -1, "protocol": "https", "video_ext": "mp4", "audio_ext": "none", "resolution": "576x1024", "dynamic_range": "SDR", "aspect_ratio": 0.56, "cookies": "sid_tt=15444ec40fa77551c3ec42e9c3a92c10; Domain=api.amemv.com; Path=/", "http_headers": {"User-Agent": "Mozilla/5.0 (Macintosh; Intel Mac OS X 10_15_7) AppleWebKit/537.36 (KHTML, like Gecko) Chrome/147.0.0.0 Safari/537.36 Edg/147.0.0.0", "Accept": "text/html,application/xhtml+xml,application/xml;q=0.9,*/*;q=0.8", "Accept-Language": "en-us,en;q=0.5", "Sec-Fetch-Mode": "navigate", "Referer": "https://www.douyin.com/"}, "format": "bytevc1_540p_316924-1 - 576x1024 (Playback video (API))"}, {"url": "https://v11-default.365yg.com/623d411c90512c4948c68e5ce3164918/6a61122c/video/tos/cn/tos-cn-ve-15/oMBqgF0j5TPPxijiqGIAQMI8BQEaQiuwkAsAI/?a=0&ch=26&cr=3&dr=0&lr=all&cd=0%7C0%7C0%7C3&cv=1&br=309&bt=309&cs=2&ds=6&ft=_7BMvR89AARXP2b6.uCd.FGcvk3.-I6Ee6AlH63TMoxJutAWPPqXteWiRtyaRfqs&mime_type=video_mp4&qs=0&rc=OjdpZjZoOjw5ZWg6PDM5O0BpM2Z0NG45cmtlOzMzNGkzM0BhY2E2MS4zX14xYDA1YDNiYSMtM2k1MmQ0LmlhLS1kLWFzcw%3D%3D&btag=80000e00010000&cquery=100H_100F_100E_103t_100I&dy_q=1784742912&feature_id=4cf169b739b0c58fabe409cdc9cebeb2&l=20260723015512FEC51E91C1EF8FE58A41", "filesize": 1138827, "ext": "mp4", "acodec": "aac", "source_preference": -1, "format_id": "bytevc1_540p_316924-2", "format_note": "Playback video", "tbr": 316, "vcodec": "h265", "fps": 30, "height": 1024, "quality": 1, "width": 576, "preference": -1, "protocol": "https", "video_ext": "mp4", "audio_ext": "none", "resolution": "576x1024", "dynamic_range": "SDR", "aspect_ratio": 0.56, "cookies": "sid_tt=15444ec40fa77551c3ec42e9c3a92c10; Domain=v11-default.365yg.com; Path=/", "http_headers": {"User-Agent": "Mozilla/5.0 (Macintosh; Intel Mac OS X 10_15_7) AppleWebKit/537.36 (KHTML, like Gecko) Chrome/147.0.0.0 Safari/537.36 Edg/147.0.0.0", "Accept": "text/html,application/xhtml+xml,application/xml;q=0.9,*/*;q=0.8", "Accept-Language": "en-us,en;q=0.5", "Sec-Fetch-Mode": "navigate", "Referer": "https://www.douyin.com/"}, "format": "bytevc1_540p_316924-2 - 576x1024 (Playback video)"}, {"url": "https://v95-ynkmtc-default.365yg.com/a158e822deb8b2c2d74644c3c33ba5ea/6a61122c/video/tos/cn/tos-cn-ve-15/oMBqgF0j5TPPxijiqGIAQMI8BQEaQiuwkAsAI/?a=0&ch=26&cr=3&dr=0&lr=all&cd=0%7C0%7C0%7C3&cv=1&br=309&bt=309&cs=2&ds=6&ft=_7BMvR89AARXP2b6.uCd.FGcvk3.-I6Ee6AlH63TMoxJutAWPPqXteWiRtyaRfqs&mime_type=video_mp4&qs=0&rc=OjdpZjZoOjw5ZWg6PDM5O0BpM2Z0NG45cmtlOzMzNGkzM0BhY2E2MS4zX14xYDA1YDNiYSMtM2k1MmQ0LmlhLS1kLWFzcw%3D%3D&btag=80000e00010000&cquery=100H_100F_100E_103t_100I&dy_q=1784742912&feature_id=4cf169b739b0c58fabe409cdc9cebeb2&l=20260723015512FEC51E91C1EF8FE58A41", "filesize": 1138827, "ext": "mp4", "acodec": "aac", "source_preference": -1, "format_id": "bytevc1_540p_316924-3", "format_note": "Playback video", "tbr": 316, "vcodec": "h265", "fps": 30, "height": 1024, "quality": 1, "width": 576, "preference": -1, "protocol": "https", "video_ext": "mp4", "audio_ext": "none", "resolution": "576x1024", "dynamic_range": "SDR", "aspect_ratio": 0.56, "cookies": "sid_tt=15444ec40fa77551c3ec42e9c3a92c10; Domain=v95-ynkmtc-default.365yg.com; Path=/", "http_headers": {"User-Agent": "Mozilla/5.0 (Macintosh; Intel Mac OS X 10_15_7) AppleWebKit/537.36 (KHTML, like Gecko) Chrome/147.0.0.0 Safari/537.36 Edg/147.0.0.0", "Accept": "text/html,application/xhtml+xml,application/xml;q=0.9,*/*;q=0.8", "Accept-Language": "en-us,en;q=0.5", "Sec-Fetch-Mode": "navigate", "Referer": "https://www.douyin.com/"}, "format": "bytevc1_540p_316924-3 - 576x1024 (Playback video)"}, {"url": "https://api-play.amemv.com/aweme/v1/play/?video_id=v0d00fg10000d8lb1h7og65k81lq6c00&line=0&file_id=f392dfd80efc400a915cb54a783e0cc0&sign=97a5fb3636b80d44b50e95eb0d73c35f&is_play_url=1&source=PackSourceEnum_AWEME_DETAIL", "filesize": 1307521, "ext": "mp4", "acodec": "aac", "source_preference": -2, "format_id": "bytevc1_540p_363869-0", "format_note": "Playback video (API)", "tbr": 363, "vcodec": "h265", "fps": 30, "height": 1024, "quality": 1, "width": 576, "preference": -1, "protocol": "https", "video_ext": "mp4", "audio_ext": "none", "resolution": "576x1024", "dynamic_range": "SDR", "aspect_ratio": 0.56, "cookies": "sid_tt=15444ec40fa77551c3ec42e9c3a92c10; Domain=api-play.amemv.com; Path=/", "http_headers": {"User-Agent": "Mozilla/5.0 (Macintosh; Intel Mac OS X 10_15_7) AppleWebKit/537.36 (KHTML, like Gecko) Chrome/147.0.0.0 Safari/537.36 Edg/147.0.0.0", "Accept": "text/html,application/xhtml+xml,application/xml;q=0.9,*/*;q=0.8", "Accept-Language": "en-us,en;q=0.5", "Sec-Fetch-Mode": "navigate", "Referer": "https://www.douyin.com/"}, "format": "bytevc1_540p_363869-0 - 576x1024 (Playback video (API))"}, {"url": "https://api.amemv.com/aweme/v1/play/?video_id=v0d00fg10000d8lb1h7og65k81lq6c00&line=1&file_id=f392dfd80efc400a915cb54a783e0cc0&sign=97a5fb3636b80d44b50e95eb0d73c35f&is_play_url=1&source=PackSourceEnum_AWEME_DETAIL", "filesize": 1307521, "ext": "mp4", "acodec": "aac", "source_preference": -2, "format_id": "bytevc1_540p_363869-1", "format_note": "Playback video (API)", "tbr": 363, "vcodec": "h265", "fps": 30, "height": 1024, "quality": 1, "width": 576, "preference": -1, "protocol": "https", "video_ext": "mp4", "audio_ext": "none", "resolution": "576x1024", "dynamic_range": "SDR", "aspect_ratio": 0.56, "cookies": "sid_tt=15444ec40fa77551c3ec42e9c3a92c10; Domain=api.amemv.com; Path=/", "http_headers": {"User-Agent": "Mozilla/5.0 (Macintosh; Intel Mac OS X 10_15_7) AppleWebKit/537.36 (KHTML, like Gecko) Chrome/147.0.0.0 Safari/537.36 Edg/147.0.0.0", "Accept": "text/html,application/xhtml+xml,application/xml;q=0.9,*/*;q=0.8", "Accept-Language": "en-us,en;q=0.5", "Sec-Fetch-Mode": "navigate", "Referer": "https://www.douyin.com/"}, "format": "bytevc1_540p_363869-1 - 576x1024 (Playback video (API))"}, {"url": "https://v11-default.365yg.com/6d794833194a638bcdecd9733d7fcc65/6a61122c/video/tos/cn/tos-cn-ve-15/oQa4QAEAUhByXw6VCRLIAGGJBVA7e3fRgAeMaW/?a=0&ch=26&cr=3&dr=0&lr=all&cd=0%7C0%7C0%7C3&cv=1&br=355&bt=355&cs=2&ds=6&ft=_7BMvR89AARXP2b6.uCd.FGcvk3.-I6Ee6AlH63TMoxJutAWPPqXteWiRtyaRfqs&mime_type=video_mp4&qs=0&rc=M2ZoO2Q4ZjRkM2ZoO2k1NkBpM2Z0NG45cmtlOzMzNGkzM0BgLTA0MV8yNi0xYy1hYTZjYSMtM2k1MmQ0LmlhLS1kLWFzcw%3D%3D&btag=80000e00010000&cquery=103t_100I_100H_100F_100E&dy_q=1784742912&feature_id=4cf169b739b0c58fabe409cdc9cebeb2&l=20260723015512FEC51E91C1EF8FE58A41", "filesize": 1307521, "ext": "mp4", "acodec": "aac", "source_preference": -1, "format_id": "bytevc1_540p_363869-2", "format_note": "Playback video", "tbr": 363, "vcodec": "h265", "fps": 30, "height": 1024, "quality": 1, "width": 576, "preference": -1, "protocol": "https", "video_ext": "mp4", "audio_ext": "none", "resolution": "576x1024", "dynamic_range": "SDR", "aspect_ratio": 0.56, "cookies": "sid_tt=15444ec40fa77551c3ec42e9c3a92c10; Domain=v11-default.365yg.com; Path=/", "http_headers": {"User-Agent": "Mozilla/5.0 (Macintosh; Intel Mac OS X 10_15_7) AppleWebKit/537.36 (KHTML, like Gecko) Chrome/147.0.0.0 Safari/537.36 Edg/147.0.0.0", "Accept": "text/html,application/xhtml+xml,application/xml;q=0.9,*/*;q=0.8", "Accept-Language": "en-us,en;q=0.5", "Sec-Fetch-Mode": "navigate", "Referer": "https://www.douyin.com/"}, "format": "bytevc1_540p_363869-2 - 576x1024 (Playback video)"}, {"url": "https://v95-ynkmtc-default.365yg.com/91325d8511e0a7f207f1ea37ca23bdac/6a61122c/video/tos/cn/tos-cn-ve-15/oQa4QAEAUhByXw6VCRLIAGGJBVA7e3fRgAeMaW/?a=0&ch=26&cr=3&dr=0&lr=all&cd=0%7C0%7C0%7C3&cv=1&br=355&bt=355&cs=2&ds=6&ft=_7BMvR89AARXP2b6.uCd.FGcvk3.-I6Ee6AlH63TMoxJutAWPPqXteWiRtyaRfqs&mime_type=video_mp4&qs=0&rc=M2ZoO2Q4ZjRkM2ZoO2k1NkBpM2Z0NG45cmtlOzMzNGkzM0BgLTA0MV8yNi0xYy1hYTZjYSMtM2k1MmQ0LmlhLS1kLWFzcw%3D%3D&btag=80000e00010000&cquery=100E_103t_100I_100H_100F&dy_q=1784742912&feature_id=4cf169b739b0c58fabe409cdc9cebeb2&l=20260723015512FEC51E91C1EF8FE58A41", "filesize": 1307521, "ext": "mp4", "acodec": "aac", "source_preference": -1, "format_id": "bytevc1_540p_363869-3", "format_note": "Playback video", "tbr": 363, "vcodec": "h265", "fps": 30, "height": 1024, "quality": 1, "width": 576, "preference": -1, "protocol": "https", "video_ext": "mp4", "audio_ext": "none", "resolution": "576x1024", "dynamic_range": "SDR", "aspect_ratio": 0.56, "cookies": "sid_tt=15444ec40fa77551c3ec42e9c3a92c10; Domain=v95-ynkmtc-default.365yg.com; Path=/", "http_headers": {"User-Agent": "Mozilla/5.0 (Macintosh; Intel Mac OS X 10_15_7) AppleWebKit/537.36 (KHTML, like Gecko) Chrome/147.0.0.0 Safari/537.36 Edg/147.0.0.0", "Accept": "text/html,application/xhtml+xml,application/xml;q=0.9,*/*;q=0.8", "Accept-Language": "en-us,en;q=0.5", "Sec-Fetch-Mode": "navigate", "Referer": "https://www.douyin.com/"}, "format": "bytevc1_540p_363869-3 - 576x1024 (Playback video)"}, {"url": "https://api-play.amemv.com/aweme/v1/play/?video_id=v0d00fg10000d8lb1h7og65k81lq6c00&line=0&file_id=e9930d8dd27546b7a7a50ea55ad4230c&sign=cc7c8e7abc63725a74bde89392461fb2&is_play_url=1&source=PackSourceEnum_AWEME_DETAIL", "filesize": 851082, "ext": "mp4", "acodec": "aac", "source_preference": -2, "format_id": "bytevc1_720p_236847-0", "format_note": "Playback video (API)", "tbr": 236, "vcodec": "h265", "fps": 30, "height": 1280, "quality": 2, "width": 720, "preference": -1, "protocol": "https", "video_ext": "mp4", "audio_ext": "none", "resolution": "720x1280", "dynamic_range": "SDR", "aspect_ratio": 0.56, "cookies": "sid_tt=15444ec40fa77551c3ec42e9c3a92c10; Domain=api-play.amemv.com; Path=/", "http_headers": {"User-Agent": "Mozilla/5.0 (Macintosh; Intel Mac OS X 10_15_7) AppleWebKit/537.36 (KHTML, like Gecko) Chrome/147.0.0.0 Safari/537.36 Edg/147.0.0.0", "Accept": "text/html,application/xhtml+xml,application/xml;q=0.9,*/*;q=0.8", "Accept-Language": "en-us,en;q=0.5", "Sec-Fetch-Mode": "navigate", "Referer": "https://www.douyin.com/"}, "format": "bytevc1_720p_236847-0 - 720x1280 (Playback video (API))"}, {"url": "https://api.amemv.com/aweme/v1/play/?video_id=v0d00fg10000d8lb1h7og65k81lq6c00&line=1&file_id=e9930d8dd27546b7a7a50ea55ad4230c&sign=cc7c8e7abc63725a74bde89392461fb2&is_play_url=1&source=PackSourceEnum_AWEME_DETAIL", "filesize": 851082, "ext": "mp4", "acodec": "aac", "source_preference": -2, "format_id": "bytevc1_720p_236847-1", "format_note": "Playback video (API)", "tbr": 236, "vcodec": "h265", "fps": 30, "height": 1280, "quality": 2, "width": 720, "preference": -1, "protocol": "https", "video_ext": "mp4", "audio_ext": "none", "resolution": "720x1280", "dynamic_range": "SDR", "aspect_ratio": 0.56, "cookies": "sid_tt=15444ec40fa77551c3ec42e9c3a92c10; Domain=api.amemv.com; Path=/", "http_headers": {"User-Agent": "Mozilla/5.0 (Macintosh; Intel Mac OS X 10_15_7) AppleWebKit/537.36 (KHTML, like Gecko) Chrome/147.0.0.0 Safari/537.36 Edg/147.0.0.0", "Accept": "text/html,application/xhtml+xml,application/xml;q=0.9,*/*;q=0.8", "Accept-Language": "en-us,en;q=0.5", "Sec-Fetch-Mode": "navigate", "Referer": "https://www.douyin.com/"}, "format": "bytevc1_720p_236847-1 - 720x1280 (Playback video (API))"}, {"url": "https://v11-default.365yg.com/db90ab75135f36df298e504a0a8fd488/6a61122c/video/tos/cn/tos-cn-ve-15/o4MMgALtRaaJewqVBzGAQGVR7AUA4CRBeWI6es/?a=0&ch=26&cr=3&dr=0&lr=all&cd=0%7C0%7C0%7C3&cv=1&br=231&bt=231&cs=2&ds=3&ft=_7BMvR89AARXP2b6.uCd.FGcvk3.-I6Ee6AlH63TMoxJutAWPPqXteWiRtyaRfqs&mime_type=video_mp4&qs=0&rc=ZjY3ZDhoODo6OTg1Z2c2PEBpM2Z0NG45cmtlOzMzNGkzM0AtL2EyXi1eXl8xNGE1LTZiYSMtM2k1MmQ0LmlhLS1kLWFzcw%3D%3D&btag=80000e00010000&cquery=100E_103t_100I_100H_100F&dy_q=1784742912&feature_id=4cf169b739b0c58fabe409cdc9cebeb2&l=20260723015512FEC51E91C1EF8FE58A41", "filesize": 851082, "ext": "mp4", "acodec": "aac", "source_preference": -1, "format_id": "bytevc1_720p_236847-2", "format_note": "Playback video", "tbr": 236, "vcodec": "h265", "fps": 30, "height": 1280, "quality": 2, "width": 720, "preference": -1, "protocol": "https", "video_ext": "mp4", "audio_ext": "none", "resolution": "720x1280", "dynamic_range": "SDR", "aspect_ratio": 0.56, "cookies": "sid_tt=15444ec40fa77551c3ec42e9c3a92c10; Domain=v11-default.365yg.com; Path=/", "http_headers": {"User-Agent": "Mozilla/5.0 (Macintosh; Intel Mac OS X 10_15_7) AppleWebKit/537.36 (KHTML, like Gecko) Chrome/147.0.0.0 Safari/537.36 Edg/147.0.0.0", "Accept": "text/html,application/xhtml+xml,application/xml;q=0.9,*/*;q=0.8", "Accept-Language": "en-us,en;q=0.5", "Sec-Fetch-Mode": "navigate", "Referer": "https://www.douyin.com/"}, "format": "bytevc1_720p_236847-2 - 720x1280 (Playback video)"}, {"url": "https://v95-ynkmtc-default.365yg.com/162b2215a40a071af39d477fd37e9804/6a61122c/video/tos/cn/tos-cn-ve-15/o4MMgALtRaaJewqVBzGAQGVR7AUA4CRBeWI6es/?a=0&ch=26&cr=3&dr=0&lr=all&cd=0%7C0%7C0%7C3&cv=1&br=231&bt=231&cs=2&ds=3&ft=_7BMvR89AARXP2b6.uCd.FGcvk3.-I6Ee6AlH63TMoxJutAWPPqXteWiRtyaRfqs&mime_type=video_mp4&qs=0&rc=ZjY3ZDhoODo6OTg1Z2c2PEBpM2Z0NG45cmtlOzMzNGkzM0AtL2EyXi1eXl8xNGE1LTZiYSMtM2k1MmQ0LmlhLS1kLWFzcw%3D%3D&btag=80000e00010000&cquery=100E_103t_100I_100H_100F&dy_q=1784742912&feature_id=4cf169b739b0c58fabe409cdc9cebeb2&l=20260723015512FEC51E91C1EF8FE58A41", "filesize": 851082, "ext": "mp4", "acodec": "aac", "source_preference": -1, "format_id": "bytevc1_720p_236847-3", "format_note": "Playback video", "tbr": 236, "vcodec": "h265", "fps": 30, "height": 1280, "quality": 2, "width": 720, "preference": -1, "protocol": "https", "video_ext": "mp4", "audio_ext": "none", "resolution": "720x1280", "dynamic_range": "SDR", "aspect_ratio": 0.56, "cookies": "sid_tt=15444ec40fa77551c3ec42e9c3a92c10; Domain=v95-ynkmtc-default.365yg.com; Path=/", "http_headers": {"User-Agent": "Mozilla/5.0 (Macintosh; Intel Mac OS X 10_15_7) AppleWebKit/537.36 (KHTML, like Gecko) Chrome/147.0.0.0 Safari/537.36 Edg/147.0.0.0", "Accept": "text/html,application/xhtml+xml,application/xml;q=0.9,*/*;q=0.8", "Accept-Language": "en-us,en;q=0.5", "Sec-Fetch-Mode": "navigate", "Referer": "https://www.douyin.com/"}, "format": "bytevc1_720p_236847-3 - 720x1280 (Playback video)"}, {"url": "https://api-play.amemv.com/aweme/v1/play/?video_id=v0d00fg10000d8lb1h7og65k81lq6c00&line=0&file_id=ba44c36d61744188858eaf3f17f72351&sign=f2981f3008bad1c82f6efdb9113de93f&is_play_url=1&source=PackSourceEnum_AWEME_DETAIL", "filesize": 1076557, "ext": "mp4", "acodec": "aac", "source_preference": -2, "format_id": "bytevc1_720p_299594-0", "format_note": "Playback video (API)", "tbr": 299, "vcodec": "h265", "fps": 30, "height": 1280, "quality": 2, "width": 720, "preference": -1, "protocol": "https", "video_ext": "mp4", "audio_ext": "none", "resolution": "720x1280", "dynamic_range": "SDR", "aspect_ratio": 0.56, "cookies": "sid_tt=15444ec40fa77551c3ec42e9c3a92c10; Domain=api-play.amemv.com; Path=/", "http_headers": {"User-Agent": "Mozilla/5.0 (Macintosh; Intel Mac OS X 10_15_7) AppleWebKit/537.36 (KHTML, like Gecko) Chrome/147.0.0.0 Safari/537.36 Edg/147.0.0.0", "Accept": "text/html,application/xhtml+xml,application/xml;q=0.9,*/*;q=0.8", "Accept-Language": "en-us,en;q=0.5", "Sec-Fetch-Mode": "navigate", "Referer": "https://www.douyin.com/"}, "format": "bytevc1_720p_299594-0 - 720x1280 (Playback video (API))"}, {"url": "https://api.amemv.com/aweme/v1/play/?video_id=v0d00fg10000d8lb1h7og65k81lq6c00&line=1&file_id=ba44c36d61744188858eaf3f17f72351&sign=f2981f3008bad1c82f6efdb9113de93f&is_play_url=1&source=PackSourceEnum_AWEME_DETAIL", "filesize": 1076557, "ext": "mp4", "acodec": "aac", "source_preference": -2, "format_id": "bytevc1_720p_299594-1", "format_note": "Playback video (API)", "tbr": 299, "vcodec": "h265", "fps": 30, "height": 1280, "quality": 2, "width": 720, "preference": -1, "protocol": "https", "video_ext": "mp4", "audio_ext": "none", "resolution": "720x1280", "dynamic_range": "SDR", "aspect_ratio": 0.56, "cookies": "sid_tt=15444ec40fa77551c3ec42e9c3a92c10; Domain=api.amemv.com; Path=/", "http_headers": {"User-Agent": "Mozilla/5.0 (Macintosh; Intel Mac OS X 10_15_7) AppleWebKit/537.36 (KHTML, like Gecko) Chrome/147.0.0.0 Safari/537.36 Edg/147.0.0.0", "Accept": "text/html,application/xhtml+xml,application/xml;q=0.9,*/*;q=0.8", "Accept-Language": "en-us,en;q=0.5", "Sec-Fetch-Mode": "navigate", "Referer": "https://www.douyin.com/"}, "format": "bytevc1_720p_299594-1 - 720x1280 (Playback video (API))"}, {"url": "https://v11-default.365yg.com/95b677f349133ef9714cb6745052e7f8/6a61122c/video/tos/cn/tos-cn-ve-15/oMxiaqABMjnTsEBB8qPPAJu0iQIEPQQ7wGiAI/?a=0&ch=26&cr=3&dr=0&lr=all&cd=0%7C0%7C0%7C3&cv=1&br=292&bt=292&cs=2&ds=3&ft=_7BMvR89AARXP2b6.uCd.FGcvk3.-I6Ee6AlH63TMoxJutAWPPqXteWiRtyaRfqs&mime_type=video_mp4&qs=0&rc=NDY6OmlpaDg7NDc0ZzY3ZEBpM2Z0NG45cmtlOzMzNGkzM0AyL2MuMF41NTUxNDMzYDFfYSMtM2k1MmQ0LmlhLS1kLWFzcw%3D%3D&btag=80000e00010000&cquery=103t_100I_100H_100F_100E&dy_q=1784742912&feature_id=4cf169b739b0c58fabe409cdc9cebeb2&l=20260723015512FEC51E91C1EF8FE58A41", "filesize": 1076557, "ext": "mp4", "acodec": "aac", "source_preference": -1, "format_id": "bytevc1_720p_299594-2", "format_note": "Playback video", "tbr": 299, "vcodec": "h265", "fps": 30, "height": 1280, "quality": 2, "width": 720, "preference": -1, "protocol": "https", "video_ext": "mp4", "audio_ext": "none", "resolution": "720x1280", "dynamic_range": "SDR", "aspect_ratio": 0.56, "cookies": "sid_tt=15444ec40fa77551c3ec42e9c3a92c10; Domain=v11-default.365yg.com; Path=/", "http_headers": {"User-Agent": "Mozilla/5.0 (Macintosh; Intel Mac OS X 10_15_7) AppleWebKit/537.36 (KHTML, like Gecko) Chrome/147.0.0.0 Safari/537.36 Edg/147.0.0.0", "Accept": "text/html,application/xhtml+xml,application/xml;q=0.9,*/*;q=0.8", "Accept-Language": "en-us,en;q=0.5", "Sec-Fetch-Mode": "navigate", "Referer": "https://www.douyin.com/"}, "format": "bytevc1_720p_299594-2 - 720x1280 (Playback video)"}, {"url": "https://v95-ynkmtc-default.365yg.com/bb6ed347b60e89211411220067a1bc51/6a61122c/video/tos/cn/tos-cn-ve-15/oMxiaqABMjnTsEBB8qPPAJu0iQIEPQQ7wGiAI/?a=0&ch=26&cr=3&dr=0&lr=all&cd=0%7C0%7C0%7C3&cv=1&br=292&bt=292&cs=2&ds=3&ft=_7BMvR89AARXP2b6.uCd.FGcvk3.-I6Ee6AlH63TMoxJutAWPPqXteWiRtyaRfqs&mime_type=video_mp4&qs=0&rc=NDY6OmlpaDg7NDc0ZzY3ZEBpM2Z0NG45cmtlOzMzNGkzM0AyL2MuMF41NTUxNDMzYDFfYSMtM2k1MmQ0LmlhLS1kLWFzcw%3D%3D&btag=80000e00010000&cquery=100F_100E_103t_100I_100H&dy_q=1784742912&feature_id=4cf169b739b0c58fabe409cdc9cebeb2&l=20260723015512FEC51E91C1EF8FE58A41", "filesize": 1076557, "ext": "mp4", "acodec": "aac", "source_preference": -1, "format_id": "bytevc1_720p_299594-3", "format_note": "Playback video", "tbr": 299, "vcodec": "h265", "fps": 30, "height": 1280, "quality": 2, "width": 720, "preference": -1, "protocol": "https", "video_ext": "mp4", "audio_ext": "none", "resolution": "720x1280", "dynamic_range": "SDR", "aspect_ratio": 0.56, "cookies": "sid_tt=15444ec40fa77551c3ec42e9c3a92c10; Domain=v95-ynkmtc-default.365yg.com; Path=/", "http_headers": {"User-Agent": "Mozilla/5.0 (Macintosh; Intel Mac OS X 10_15_7) AppleWebKit/537.36 (KHTML, like Gecko) Chrome/147.0.0.0 Safari/537.36 Edg/147.0.0.0", "Accept": "text/html,application/xhtml+xml,application/xml;q=0.9,*/*;q=0.8", "Accept-Language": "en-us,en;q=0.5", "Sec-Fetch-Mode": "navigate", "Referer": "https://www.douyin.com/"}, "format": "bytevc1_720p_299594-3 - 720x1280 (Playback video)"}, {"url": "https://api-play.amemv.com/aweme/v1/play/?video_id=v0d00fg10000d8lb1h7og65k81lq6c00&line=0&file_id=bb5cbda4b17442b9af97886ab48bee0d&sign=327d98fa01d2e22ac3b1addd94b3da42&is_play_url=1&source=PackSourceEnum_AWEME_DETAIL", "filesize": 1544962, "ext": "mp4", "acodec": "aac", "source_preference": -2, "format_id": "bytevc1_720p_429947-0", "format_note": "Playback video (API)", "tbr": 429, "vcodec": "h265", "fps": 30, "height": 1280, "quality": 2, "width": 720, "preference": -1, "protocol": "https", "video_ext": "mp4", "audio_ext": "none", "resolution": "720x1280", "dynamic_range": "SDR", "aspect_ratio": 0.56, "cookies": "sid_tt=15444ec40fa77551c3ec42e9c3a92c10; Domain=api-play.amemv.com; Path=/", "http_headers": {"User-Agent": "Mozilla/5.0 (Macintosh; Intel Mac OS X 10_15_7) AppleWebKit/537.36 (KHTML, like Gecko) Chrome/147.0.0.0 Safari/537.36 Edg/147.0.0.0", "Accept": "text/html,application/xhtml+xml,application/xml;q=0.9,*/*;q=0.8", "Accept-Language": "en-us,en;q=0.5", "Sec-Fetch-Mode": "navigate", "Referer": "https://www.douyin.com/"}, "format": "bytevc1_720p_429947-0 - 720x1280 (Playback video (API))"}, {"url": "https://api.amemv.com/aweme/v1/play/?video_id=v0d00fg10000d8lb1h7og65k81lq6c00&line=1&file_id=bb5cbda4b17442b9af97886ab48bee0d&sign=327d98fa01d2e22ac3b1addd94b3da42&is_play_url=1&source=PackSourceEnum_AWEME_DETAIL", "filesize": 1544962, "ext": "mp4", "acodec": "aac", "source_preference": -2, "format_id": "bytevc1_720p_429947-1", "format_note": "Playback video (API)", "tbr": 429, "vcodec": "h265", "fps": 30, "height": 1280, "quality": 2, "width": 720, "preference": -1, "protocol": "https", "video_ext": "mp4", "audio_ext": "none", "resolution": "720x1280", "dynamic_range": "SDR", "aspect_ratio": 0.56, "cookies": "sid_tt=15444ec40fa77551c3ec42e9c3a92c10; Domain=api.amemv.com; Path=/", "http_headers": {"User-Agent": "Mozilla/5.0 (Macintosh; Intel Mac OS X 10_15_7) AppleWebKit/537.36 (KHTML, like Gecko) Chrome/147.0.0.0 Safari/537.36 Edg/147.0.0.0", "Accept": "text/html,application/xhtml+xml,application/xml;q=0.9,*/*;q=0.8", "Accept-Language": "en-us,en;q=0.5", "Sec-Fetch-Mode": "navigate", "Referer": "https://www.douyin.com/"}, "format": "bytevc1_720p_429947-1 - 720x1280 (Playback video (API))"}, {"url": "https://v11-default.365yg.com/7f2bb1f7fde739bfe09fb7cf821ab8ce/6a61122c/video/tos/cn/tos-cn-ve-15/ogAdZEQgNJAFAEr8Qh9YoKfNeDDpABCIGgLqgq/?a=0&ch=26&cr=3&dr=0&lr=all&cd=0%7C0%7C0%7C3&cv=1&br=419&bt=419&cs=2&ds=3&ft=_7BMvR89AARXP2b6.uCd.FGcvk3.-I6Ee6AlH63TMoxJutAWPPqXteWiRtyaRfqs&mime_type=video_mp4&qs=0&rc=Z2hlN2Q7Omk8NTc0N2dmZUBpM2Z0NG45cmtlOzMzNGkzM0AtYjVfMzU2Xl8xNF9eXzJfYSMtM2k1MmQ0LmlhLS1kLWFzcw%3D%3D&btag=80000e00010000&cquery=100E_103t_100I_100H_100F&dy_q=1784742912&feature_id=4cf169b739b0c58fabe409cdc9cebeb2&l=20260723015512FEC51E91C1EF8FE58A41", "filesize": 1544962, "ext": "mp4", "acodec": "aac", "source_preference": -1, "format_id": "bytevc1_720p_429947-2", "format_note": "Playback video", "tbr": 429, "vcodec": "h265", "fps": 30, "height": 1280, "quality": 2, "width": 720, "preference": -1, "protocol": "https", "video_ext": "mp4", "audio_ext": "none", "resolution": "720x1280", "dynamic_range": "SDR", "aspect_ratio": 0.56, "cookies": "sid_tt=15444ec40fa77551c3ec42e9c3a92c10; Domain=v11-default.365yg.com; Path=/", "http_headers": {"User-Agent": "Mozilla/5.0 (Macintosh; Intel Mac OS X 10_15_7) AppleWebKit/537.36 (KHTML, like Gecko) Chrome/147.0.0.0 Safari/537.36 Edg/147.0.0.0", "Accept": "text/html,application/xhtml+xml,application/xml;q=0.9,*/*;q=0.8", "Accept-Language": "en-us,en;q=0.5", "Sec-Fetch-Mode": "navigate", "Referer": "https://www.douyin.com/"}, "format": "bytevc1_720p_429947-2 - 720x1280 (Playback video)"}, {"url": "https://v95-ynkmtc-default.365yg.com/b0b8dcfd0cdbeaaab1452b6f5c3798eb/6a61122c/video/tos/cn/tos-cn-ve-15/ogAdZEQgNJAFAEr8Qh9YoKfNeDDpABCIGgLqgq/?a=0&ch=26&cr=3&dr=0&lr=all&cd=0%7C0%7C0%7C3&cv=1&br=419&bt=419&cs=2&ds=3&ft=_7BMvR89AARXP2b6.uCd.FGcvk3.-I6Ee6AlH63TMoxJutAWPPqXteWiRtyaRfqs&mime_type=video_mp4&qs=0&rc=Z2hlN2Q7Omk8NTc0N2dmZUBpM2Z0NG45cmtlOzMzNGkzM0AtYjVfMzU2Xl8xNF9eXzJfYSMtM2k1MmQ0LmlhLS1kLWFzcw%3D%3D&btag=80000e00010000&cquery=103t_100I_100H_100F_100E&dy_q=1784742912&feature_id=4cf169b739b0c58fabe409cdc9cebeb2&l=20260723015512FEC51E91C1EF8FE58A41", "filesize": 1544962, "ext": "mp4", "acodec": "aac", "source_preference": -1, "format_id": "bytevc1_720p_429947-3", "format_note": "Playback video", "tbr": 429, "vcodec": "h265", "fps": 30, "height": 1280, "quality": 2, "width": 720, "preference": -1, "protocol": "https", "video_ext": "mp4", "audio_ext": "none", "resolution": "720x1280", "dynamic_range": "SDR", "aspect_ratio": 0.56, "cookies": "sid_tt=15444ec40fa77551c3ec42e9c3a92c10; Domain=v95-ynkmtc-default.365yg.com; Path=/", "http_headers": {"User-Agent": "Mozilla/5.0 (Macintosh; Intel Mac OS X 10_15_7) AppleWebKit/537.36 (KHTML, like Gecko) Chrome/147.0.0.0 Safari/537.36 Edg/147.0.0.0", "Accept": "text/html,application/xhtml+xml,application/xml;q=0.9,*/*;q=0.8", "Accept-Language": "en-us,en;q=0.5", "Sec-Fetch-Mode": "navigate", "Referer": "https://www.douyin.com/"}, "format": "bytevc1_720p_429947-3 - 720x1280 (Playback video)"}, {"url": "https://api-play.amemv.com/aweme/v1/play/?video_id=v0d00fg10000d8lb1h7og65k81lq6c00&line=0&file_id=f645c6f1f8124f5a97883e1afa1fe247&sign=97479f40437702a9fcbd1314cd1ebf25&is_play_url=1&source=PackSourceEnum_AWEME_DETAIL", "filesize": 2125667, "ext": "mp4", "acodec": "aac", "source_preference": -2, "format_id": "bytevc1_720p_591551-0", "format_note": "Playback video (API)", "tbr": 591, "vcodec": "h265", "fps": 30, "height": 1280, "quality": 2, "width": 720, "preference": -1, "protocol": "https", "video_ext": "mp4", "audio_ext": "none", "resolution": "720x1280", "dynamic_range": "SDR", "aspect_ratio": 0.56, "cookies": "sid_tt=15444ec40fa77551c3ec42e9c3a92c10; Domain=api-play.amemv.com; Path=/", "http_headers": {"User-Agent": "Mozilla/5.0 (Macintosh; Intel Mac OS X 10_15_7) AppleWebKit/537.36 (KHTML, like Gecko) Chrome/147.0.0.0 Safari/537.36 Edg/147.0.0.0", "Accept": "text/html,application/xhtml+xml,application/xml;q=0.9,*/*;q=0.8", "Accept-Language": "en-us,en;q=0.5", "Sec-Fetch-Mode": "navigate", "Referer": "https://www.douyin.com/"}, "format": "bytevc1_720p_591551-0 - 720x1280 (Playback video (API))"}, {"url": "https://api.amemv.com/aweme/v1/play/?video_id=v0d00fg10000d8lb1h7og65k81lq6c00&line=1&file_id=f645c6f1f8124f5a97883e1afa1fe247&sign=97479f40437702a9fcbd1314cd1ebf25&is_play_url=1&source=PackSourceEnum_AWEME_DETAIL", "filesize": 2125667, "ext": "mp4", "acodec": "aac", "source_preference": -2, "format_id": "bytevc1_720p_591551-1", "format_note": "Playback video (API)", "tbr": 591, "vcodec": "h265", "fps": 30, "height": 1280, "quality": 2, "width": 720, "preference": -1, "protocol": "https", "video_ext": "mp4", "audio_ext": "none", "resolution": "720x1280", "dynamic_range": "SDR", "aspect_ratio": 0.56, "cookies": "sid_tt=15444ec40fa77551c3ec42e9c3a92c10; Domain=api.amemv.com; Path=/", "http_headers": {"User-Agent": "Mozilla/5.0 (Macintosh; Intel Mac OS X 10_15_7) AppleWebKit/537.36 (KHTML, like Gecko) Chrome/147.0.0.0 Safari/537.36 Edg/147.0.0.0", "Accept": "text/html,application/xhtml+xml,application/xml;q=0.9,*/*;q=0.8", "Accept-Language": "en-us,en;q=0.5", "Sec-Fetch-Mode": "navigate", "Referer": "https://www.douyin.com/"}, "format": "bytevc1_720p_591551-1 - 720x1280 (Playback video (API))"}, {"url": "https://v11-default.365yg.com/75adbb4e08d8bcf88e6b5d34d509fce0/6a61122c/video/tos/cn/tos-cn-ve-15/ooYQMEi0PsxCAQi8ijqIQqGqIPAaBTwhKu1AB/?a=0&ch=26&cr=3&dr=0&lr=all&cd=0%7C0%7C0%7C3&cv=1&br=577&bt=577&cs=2&ds=3&ft=_7BMvR89AARXP2b6.uCd.FGcvk3.-I6Ee6AlH63TMoxJutAWPPqXteWiRtyaRfqs&mime_type=video_mp4&qs=0&rc=OjVpZGRoOzpkaTU7NDk4OUBpM2Z0NG45cmtlOzMzNGkzM0AxYi5jLjA1NjIxLmNjYDFjYSMtM2k1MmQ0LmlhLS1kLWFzcw%3D%3D&btag=80000e00010000&cquery=100H_100F_100E_103t_100I&dy_q=1784742912&feature_id=4cf169b739b0c58fabe409cdc9cebeb2&l=20260723015512FEC51E91C1EF8FE58A41", "filesize": 2125667, "ext": "mp4", "acodec": "aac", "source_preference": -1, "format_id": "bytevc1_720p_591551-2", "format_note": "Playback video", "tbr": 591, "vcodec": "h265", "fps": 30, "height": 1280, "quality": 2, "width": 720, "preference": -1, "protocol": "https", "video_ext": "mp4", "audio_ext": "none", "resolution": "720x1280", "dynamic_range": "SDR", "aspect_ratio": 0.56, "cookies": "sid_tt=15444ec40fa77551c3ec42e9c3a92c10; Domain=v11-default.365yg.com; Path=/", "http_headers": {"User-Agent": "Mozilla/5.0 (Macintosh; Intel Mac OS X 10_15_7) AppleWebKit/537.36 (KHTML, like Gecko) Chrome/147.0.0.0 Safari/537.36 Edg/147.0.0.0", "Accept": "text/html,application/xhtml+xml,application/xml;q=0.9,*/*;q=0.8", "Accept-Language": "en-us,en;q=0.5", "Sec-Fetch-Mode": "navigate", "Referer": "https://www.douyin.com/"}, "format": "bytevc1_720p_591551-2 - 720x1280 (Playback video)"}, {"url": "https://v95-ynkmtc-default.365yg.com/ec30044da203678b03e7807cca5aa99c/6a61122c/video/tos/cn/tos-cn-ve-15/ooYQMEi0PsxCAQi8ijqIQqGqIPAaBTwhKu1AB/?a=0&ch=26&cr=3&dr=0&lr=all&cd=0%7C0%7C0%7C3&cv=1&br=577&bt=577&cs=2&ds=3&ft=_7BMvR89AARXP2b6.uCd.FGcvk3.-I6Ee6AlH63TMoxJutAWPPqXteWiRtyaRfqs&mime_type=video_mp4&qs=0&rc=OjVpZGRoOzpkaTU7NDk4OUBpM2Z0NG45cmtlOzMzNGkzM0AxYi5jLjA1NjIxLmNjYDFjYSMtM2k1MmQ0LmlhLS1kLWFzcw%3D%3D&btag=80000e00010000&cquery=103t_100I_100H_100F_100E&dy_q=1784742912&feature_id=4cf169b739b0c58fabe409cdc9cebeb2&l=20260723015512FEC51E91C1EF8FE58A41", "filesize": 2125667, "ext": "mp4", "acodec": "aac", "source_preference": -1, "format_id": "bytevc1_720p_591551-3", "format_note": "Playback video", "tbr": 591, "vcodec": "h265", "fps": 30, "height": 1280, "quality": 2, "width": 720, "preference": -1, "protocol": "https", "video_ext": "mp4", "audio_ext": "none", "resolution": "720x1280", "dynamic_range": "SDR", "aspect_ratio": 0.56, "cookies": "sid_tt=15444ec40fa77551c3ec42e9c3a92c10; Domain=v95-ynkmtc-default.365yg.com; Path=/", "http_headers": {"User-Agent": "Mozilla/5.0 (Macintosh; Intel Mac OS X 10_15_7) AppleWebKit/537.36 (KHTML, like Gecko) Chrome/147.0.0.0 Safari/537.36 Edg/147.0.0.0", "Accept": "text/html,application/xhtml+xml,application/xml;q=0.9,*/*;q=0.8", "Accept-Language": "en-us,en;q=0.5", "Sec-Fetch-Mode": "navigate", "Referer": "https://www.douyin.com/"}, "format": "bytevc1_720p_591551-3 - 720x1280 (Playback video)"}], "subtitles": {}, "thumbnails": [{"id": "dynamic_cover", "url": "https://p11-sign.douyinpic.com/obj/tos-cn-i-0813c001/oA7sAqhiVmE4FAM1AZAIes7iqfA701ANABLCgo?lk3s=138a59ce&x-expires=1785949200&x-signature=BkIEQWqouqS58d5T36zCLPsQ7uE%3D&from=327834062_large&s=PackSourceEnum_AWEME_DETAIL&se=false&sc=dynamic_cover&biz_tag=aweme_video&l=20260723015512FEC51E91C1EF8FE58A41", "preference": -2}, {"id": "dynamic_cover", "url": "https://p26-sign.douyinpic.com/obj/tos-cn-i-0813c001/oA7sAqhiVmE4FAM1AZAIes7iqfA701ANABLCgo?lk3s=138a59ce&x-expires=1785949200&x-signature=tLDSYZvnhsgJkQPgjRTqDKJzu4w%3D&from=327834062_large&s=PackSourceEnum_AWEME_DETAIL&se=false&sc=dynamic_cover&biz_tag=aweme_video&l=20260723015512FEC51E91C1EF8FE58A41", "preference": -2}, {"id": "dynamic_cover", "url": "https://p5-sign.douyinpic.com/obj/tos-cn-i-0813c001/oA7sAqhiVmE4FAM1AZAIes7iqfA701ANABLCgo?lk3s=138a59ce&x-expires=1785949200&x-signature=BL5n%2F%2FBfqYwIfcXJp1g9LDm4GUI%3D&from=327834062_large&s=PackSourceEnum_AWEME_DETAIL&se=false&sc=dynamic_cover&biz_tag=aweme_video&l=20260723015512FEC51E91C1EF8FE58A41", "preference": -2}, {"id": "cover", "url": "https://p11-sign.douyinpic.com/tos-cn-i-0813c001/oA7sAqhiVmE4FAM1AZAIes7iqfA701ANABLCgo~c5_300x400.jpeg?lk3s=138a59ce&x-expires=1785949200&x-signature=Zg2bDE%2BtdmMojRfSSMnKHT6Qa9Q%3D&from=327834062_large&s=PackSourceEnum_AWEME_DETAIL&se=false&sc=cover&biz_tag=aweme_video&l=20260723015512FEC51E91C1EF8FE58A41", "preference": -1}, {"id": "cover", "url": "https://p26-sign.douyinpic.com/tos-cn-i-0813c001/oA7sAqhiVmE4FAM1AZAIes7iqfA701ANABLCgo~c5_300x400.jpeg?lk3s=138a59ce&x-expires=1785949200&x-signature=GOkpfBXnETYj0dQDIu%2FNPE0XvY0%3D&from=327834062_large&s=PackSourceEnum_AWEME_DETAIL&se=false&sc=cover&biz_tag=aweme_video&l=20260723015512FEC51E91C1EF8FE58A41", "preference": -1}, {"id": "cover", "url": "https://p5-sign.douyinpic.com/tos-cn-i-0813c001/oA7sAqhiVmE4FAM1AZAIes7iqfA701ANABLCgo~c5_300x400.jpeg?lk3s=138a59ce&x-expires=1785949200&x-signature=8eDSNOR03FI50svw7cNf9lxz1Ko%3D&from=327834062_large&s=PackSourceEnum_AWEME_DETAIL&se=false&sc=cover&biz_tag=aweme_video&l=20260723015512FEC51E91C1EF8FE58A41", "preference": -1}, {"id": "origin_cover", "url": "https://p11-sign.douyinpic.com/tos-cn-p-0015/oUsAjqY0IIPmMPuAQIaiAqBTNGiGQbiBxJsAw~tplv-dy-360p.jpeg?lk3s=138a59ce&x-expires=1785949200&x-signature=JvC08HhCxvYb3g3NTnKSio4E7ys%3D&from=327834062&s=PackSourceEnum_AWEME_DETAIL&se=false&sc=origin_cover&biz_tag=aweme_video&l=20260723015512FEC51E91C1EF8FE58A41", "preference": -1}, {"id": "origin_cover", "url": "https://p26-sign.douyinpic.com/tos-cn-p-0015/oUsAjqY0IIPmMPuAQIaiAqBTNGiGQbiBxJsAw~tplv-dy-360p.jpeg?lk3s=138a59ce&x-expires=1785949200&x-signature=JDEiEbyhiMYm2oJuOv2%2FyHbBcag%3D&from=327834062&s=PackSourceEnum_AWEME_DETAIL&se=false&sc=origin_cover&biz_tag=aweme_video&l=20260723015512FEC51E91C1EF8FE58A41", "preference": -1}, {"id": "origin_cover", "url": "https://p5-ex-gddgtc-sign.douyinpic.com/tos-cn-p-0015/oUsAjqY0IIPmMPuAQIaiAqBTNGiGQbiBxJsAw~tplv-dy-360p.jpeg?lk3s=138a59ce&x-expires=1785949200&x-signature=GxVobzrmgRq4ZCOnuDr7esiEGj0%3D&from=327834062&s=PackSourceEnum_AWEME_DETAIL&se=false&sc=origin_cover&biz_tag=aweme_video&l=20260723015512FEC51E91C1EF8FE58A41", "preference": -1}], "duration": 28, "_format_sort_fields": ["quality", "codec", "size", "br"], "webpage_url": "https://www.douyin.com/video/7650121317510341354?previous_page=app_code_link", "webpage_url_basename": "7650121317510341354", "webpage_url_domain": "douyin.com", "extractor": "Douyin", "extractor_key": "Douyin", "thumbnail": "https://p5-ex-gddgtc-sign.douyinpic.com/tos-cn-p-0015/oUsAjqY0IIPmMPuAQIaiAqBTNGiGQbiBxJsAw~tplv-dy-360p.jpeg?lk3s=138a59ce&x-expires=1785949200&x-signature=GxVobzrmgRq4ZCOnuDr7esiEGj0%3D&from=327834062&s=PackSourceEnum_AWEME_DETAIL&se=false&sc=origin_cover&biz_tag=aweme_video&l=20260723015512FEC51E91C1EF8FE58A41", "display_id": "7650121317510341354", "fulltitle": "感觉这地方有魔力就算不化妆也拍的很好看 #apink #nonono #dance #抖音潮流舞蹈大赛 #Rightcell牛仔裤", "duration_string": "28", "upload_date": "20260611", "artist": "Apink", "epoch": 1784742912, "url": "https://v95-ynkmtc-default.365yg.com/ec30044da203678b03e7807cca5aa99c/6a61122c/video/tos/cn/tos-cn-ve-15/ooYQMEi0PsxCAQi8ijqIQqGqIPAaBTwhKu1AB/?a=0&ch=26&cr=3&dr=0&lr=all&cd=0%7C0%7C0%7C3&cv=1&br=577&bt=577&cs=2&ds=3&ft=_7BMvR89AARXP2b6.uCd.FGcvk3.-I6Ee6AlH63TMoxJutAWPPqXteWiRtyaRfqs&mime_type=video_mp4&qs=0&rc=OjVpZGRoOzpkaTU7NDk4OUBpM2Z0NG45cmtlOzMzNGkzM0AxYi5jLjA1NjIxLmNjYDFjYSMtM2k1MmQ0LmlhLS1kLWFzcw%3D%3D&btag=80000e00010000&cquery=103t_100I_100H_100F_100E&dy_q=1784742912&feature_id=4cf169b739b0c58fabe409cdc9cebeb2&l=20260723015512FEC51E91C1EF8FE58A41", "filesize": 2125667, "ext": "mp4", "acodec": "aac", "source_preference": -1, "format_id": "bytevc1_720p_591551-3", "format_note": "Playback video", "tbr": 591, "vcodec": "h265", "fps": 30, "height": 1280, "quality": 2, "width": 720, "preference": -1, "protocol": "https", "video_ext": "mp4", "audio_ext": "none", "resolution": "720x1280", "dynamic_range": "SDR", "aspect_ratio": 0.56, "cookies": "sid_tt=15444ec40fa77551c3ec42e9c3a92c10; Domain=v95-ynkmtc-default.365yg.com; Path=/", "http_headers": {"User-Agent": "Mozilla/5.0 (Macintosh; Intel Mac OS X 10_15_7) AppleWebKit/537.36 (KHTML, like Gecko) Chrome/147.0.0.0 Safari/537.36 Edg/147.0.0.0", "Accept": "text/html,application/xhtml+xml,application/xml;q=0.9,*/*;q=0.8", "Accept-Language": "en-us,en;q=0.5", "Sec-Fetch-Mode": "navigate", "Referer": "https://www.douyin.com/"}, "format": "bytevc1_720p_591551-3 - 720x1280 (Playback video)", "_type": "video", "_version": {"version": "2026.07.04", "release_git_head": "997fa140840a08df3938b40da470c78049fef1f6", "repository": "yt-dlp/yt-dlp"}}