{
  "id": "les_ee6a5b2a0d50",
  "title": "2026-04-19 04:51",
  "source_url": "https://v.douyin.com/GOMwE1ygT3Y/",
  "duration": 7.67,
  "bpm": 143.55,
  "video_url": "/videos/les_ee6a5b2a0d50.mp4",
  "thumbnail": "/thumbs/les_ee6a5b2a0d50_seg_000.jpg",
  "confirmed": false,
  "beat_quality": "high",
  "beats": [
    0.49,
    0.93,
    1.37,
    1.79,
    2.21,
    2.62,
    3.02,
    3.46,
    3.88,
    4.3,
    4.71,
    5.15,
    5.57,
    5.99,
    6.41,
    6.8,
    7.2
  ],
  "sections": [
    {
      "id": "intro",
      "label": "前奏",
      "start": 0.0,
      "end": 0.91
    },
    {
      "id": "chorus_1",
      "label": "副歌 1",
      "start": 0.91,
      "end": 3.41
    },
    {
      "id": "chorus_2",
      "label": "副歌 2",
      "start": 3.41,
      "end": 5.5
    },
    {
      "id": "outro",
      "label": "尾声",
      "start": 5.5,
      "end": 7.67
    }
  ],
  "segments": [
    {
      "id": "seg_000",
      "lesson_id": "les_ee6a5b2a0d50",
      "index": 0,
      "section": "chorus_1",
      "section_label": "副歌 1",
      "start": 0.49,
      "end": 3.88,
      "duration": 3.39,
      "beat_count": 8,
      "thumbnail": "/thumbs/les_ee6a5b2a0d50_seg_000.jpg",
      "clip_url": "/clips/les_ee6a5b2a0d50_seg_000.mp4",
      "difficulty": 2,
      "is_still": false,
      "ai_description": "副歌 1·动作平缓,幅度较小",
      "user_edited": false,
      "teaching": {
        "status": "ready",
        "summary": "双脚交替点地，手臂向外伸展摆动",
        "steps": [
          {
            "beats": "1-2",
            "content": "左脚点地，双臂自然下垂；右脚点地，双臂向两侧平举"
          },
          {
            "beats": "3-4",
            "content": "重心移至左腿，右腿抬起膝盖；双手握拳置于腰间"
          },
          {
            "beats": "5-6",
            "content": "右脚落地，双臂向上举过头顶；左脚跟上，双臂放下"
          },
          {
            "beats": "7-8",
            "content": "左脚向前迈出一步，双臂向两侧打开；右脚跟上，身体转向右侧"
          }
        ],
        "tips": [
          "保持节奏感，动作流畅衔接",
          "注意重心转移，避免僵硬",
          "面部表情跟随音乐展现活力"
        ],
        "generated_at": "2026-04-18T20:52:07Z"
      },
      "deleted": false
    },
    {
      "id": "seg_001",
      "lesson_id": "les_ee6a5b2a0d50",
      "index": 1,
      "section": "outro",
      "section_label": "尾声",
      "start": 3.88,
      "end": 7.2,
      "duration": 3.32,
      "beat_count": 8,
      "thumbnail": "/thumbs/les_ee6a5b2a0d50_seg_001.jpg",
      "clip_url": "/clips/les_ee6a5b2a0d50_seg_001.mp4",
      "difficulty": 4,
      "is_still": false,
      "ai_description": "尾声·节奏紧凑,动作幅度大",
      "user_edited": false,
      "teaching": {
        "status": "ready",
        "summary": "快速身体波浪与脚步移动结合",
        "steps": [
          {
            "beats": "1-2",
            "content": "双手胸前交叠，身体向右侧倾斜，左腿支撑，右腿微屈"
          },
          {
            "beats": "3-4",
            "content": "身体重心转移到右腿，左腿向外迈出一步，同时头部和手臂跟随身体向左侧摆动"
          },
          {
            "beats": "5-6",
            "content": "进行快速的身体波浪动作，从头部开始向下传递至臀部，同时左腿向前迈出一步"
          },
          {
            "beats": "7-8",
            "content": "继续身体波浪，同时右腿向前迈出一步，双臂伴随波浪自然摆动"
          }
        ],
        "tips": [
          "保持身体波浪的流畅性，注意节奏感",
          "脚步移动要轻盈，避免过大动作影响整体协调",
          "头部和手臂的摆动要与身体波浪同步，增强表现力"
        ],
        "generated_at": "2026-04-18T20:52:14Z"
      },
      "deleted": false
    }
  ]
}